database_connections/DatabaseConnection.py
database_connections/Query.py
database_connections/TJEncryptPassword.py
database_connections/__init__.py
database_connections/__main__.py
database_connections/password_encryption.py
database_connections/sql_support_functions.py
database_connections/Connections/__init__.py
database_connections/Connections/athena.py
database_connections/Connections/databricks.py
database_connections/Connections/oracle.py
database_connections/Connections/redshift.py
database_connections/Connections/sqlite.py
database_connections/Connections/teradata.py
kabbes_database_connections-0.7.0.dist-info/LICENSE
kabbes_database_connections-0.7.0.dist-info/METADATA
kabbes_database_connections-0.7.0.dist-info/WHEEL
kabbes_database_connections-0.7.0.dist-info/top_level.txt
kabbes_database_connections-0.7.0.dist-info/RECORD
