Metadata-Version: 2.1
Name: kabbes-database-connections
Version: 0.7.0
Summary: Provides database-agnostic connection tools
Home-page: https://pypi.org/project/kabbes-database-connections/
Author: James Kabbes
Author-email: james.kabbes@gmail.com
Project-URL: GitHub, https://github.com/jameskabbes/database_connections
Project-URL: Documentation, https://jameskabbes.github.io/database_connections
Classifier: Programming Language :: Python :: 3
Classifier: License :: OSI Approved :: MIT License
Classifier: Operating System :: OS Independent
Requires-Python: >=3.7
License-File: LICENSE
Requires-Dist: kabbes-py-starter
Requires-Dist: kabbes-parent-class
Requires-Dist: kabbes-dir-ops
Requires-Dist: kabbes-user-profile
Requires-Dist: cryptography
Requires-Dist: teradatasql
Requires-Dist: pandas
Requires-Dist: pysqlite3
Requires-Dist: sqlalchemy
Requires-Dist: databricks-sql-connector
Requires-Dist: cx-Oracle
Requires-Dist: pyathena
